<?xml version="1.0" encoding="utf-8"?>
<Data>
  <Id>36066b6f-f24c-4a0a-a4b7-60f855d2e274</Id>
  <Name>Xml Laden ohne Slash</Name>
  <UserId>d601adbc-eee3-436f-b657-c9f4969a449a</UserId>
  <ProjectId>58f1500a-c8e2-4f52-a066-8ab5372e5c55</ProjectId>
  <Text>Im Momemt gibt es Probleme mit Texten, die eine Slash drin haben, da man dies beim speichern und laden trennt...Muss gefixt werden</Text>
  <Created>18.06.2019 18:47:02</Created>
  <ExpectedTime>0,5</ExpectedTime>
  <UsedTime>0,18125</UsedTime>
  <Priority>High</Priority>
  <Status>Finished</Status>
</Data>